netrun_cors/__init__.py
netrun_cors/config.py
netrun_cors/middleware.py
netrun_cors/presets.py
netrun_cors-2.1.0.dist-info/METADATA
netrun_cors-2.1.0.dist-info/WHEEL
netrun_cors-2.1.0.dist-info/licenses/LICENSE
netrun_cors-2.1.0.dist-info/RECORD
