Metadata-Version: 2.4
Name: netrun-cors
Version: 2.1.0
Summary: Enterprise CORS middleware presets for FastAPI applications
Project-URL: Homepage, https://netrunsystems.com
Project-URL: Documentation, https://github.com/netrunsystems/netrun-cors
Project-URL: Repository, https://github.com/netrunsystems/netrun-cors
Project-URL: Issues, https://github.com/netrunsystems/netrun-cors/issues
Author-email: Netrun Systems <support@netrunsystems.com>
License: MIT
License-File: LICENSE
Keywords: azure,cors,fastapi,middleware,oauth,security,starlette
Classifier: Development Status :: 5 - Production/Stable
Classifier: Framework :: FastAPI
Classifier: Intended Audience :: Developers
Classifier: License :: OSI Approved :: MIT License
Classifier: Programming Language :: Python :: 3
Classifier: Programming Language :: Python :: 3.11
Classifier: Programming Language :: Python :: 3.12
Classifier: Topic :: Internet :: WWW/HTTP :: HTTP Servers
Classifier: Topic :: Internet :: WWW/HTTP :: WSGI :: Middleware
Classifier: Topic :: Security
Requires-Python: >=3.11
Requires-Dist: fastapi>=0.109.0
Requires-Dist: netrun-core>=2.0.0
Requires-Dist: pydantic-settings>=2.0.0
Requires-Dist: pydantic>=2.0.0
Requires-Dist: starlette>=0.27.0
Provides-Extra: dev
Requires-Dist: black>=23.0.0; extra == 'dev'
Requires-Dist: httpx>=0.25.0; extra == 'dev'
Requires-Dist: mypy>=1.7.0; extra == 'dev'
Requires-Dist: netrun-logging>=2.0.0; extra == 'dev'
Requires-Dist: pytest-asyncio>=0.21.0; extra == 'dev'
Requires-Dist: pytest-cov>=4.1.0; extra == 'dev'
Requires-Dist: pytest>=7.4.0; extra == 'dev'
Requires-Dist: ruff>=0.1.0; extra == 'dev'
Provides-Extra: logging
Requires-Dist: netrun-logging>=2.0.0; extra == 'logging'
